normalkl/__init__.py
normalkl/auto_kl.py
normalkl/kl.py
normalkl/logdet.py
normalkl/optimal.py
normalkl/quadratic.py
normalkl/trace.py
normalkl/util.py
normalkl-0.1.16.dist-info/METADATA
normalkl-0.1.16.dist-info/WHEEL
normalkl-0.1.16.dist-info/top_level.txt
normalkl-0.1.16.dist-info/RECORD
