Metadata-Version: 2.1
Name: normalkl
Version: 0.1.16
Summary: A PyTorch package for computing KL divergences between normal distributions.
Home-page: https://github.com/tychovdo/normal-kl
Author: Tycho van der Ouderaa
Author-email: tychovdo@gmail.com
License: MIT
Classifier: Programming Language :: Python :: 3
Classifier: License :: OSI Approved :: MIT License
Classifier: Operating System :: OS Independent
Requires-Python: >=3.6
Requires-Dist: torch
